named_enum/__init__.py
named_enum/enum.py
named_enum/meta.py
named_enum-1.4.0.dist-info/LICENSE
named_enum-1.4.0.dist-info/METADATA
named_enum-1.4.0.dist-info/WHEEL
named_enum-1.4.0.dist-info/RECORD
