Metadata-Version: 2.1
Name: named-enum
Version: 1.4.0
Summary: Python named enumeration, which extends the built-in Enum class with extra features.
Home-page: https://github.com/zhiwei2017/named_enum
License: MIT
Keywords: Operating System :: OS Independent,License :: OSI Approved :: MIT License,Development Status :: 5 - Production/Stable,Programming Language :: Python,Programming Language :: Python :: 3,Programming Language :: Python :: 3.8,Programming Language :: Python :: 3.9,Programming Language :: Python :: 3.10,Programming Language :: Python :: 3.11,Programming Language :: Python :: 3.12,Programming Language :: Python :: Implementation,Topic :: Utilities,Natural Language :: English,Intended Audienc
Author: Zhiwei Zhang
Author-email: zhiwei2017@gmail.com
Requires-Python: >=3.8.1,<4.0.0
Classifier: License :: OSI Approved :: MIT License
Classifier: Programming Language :: Python :: 3
Classifier: Programming Language :: Python :: 3.9
Classifier: Programming Language :: Python :: 3.10
Classifier: Programming Language :: Python :: 3.11
Project-URL: Documentation, https://zhiwei2017.github.io/named_enum/
Project-URL: Repository, https://github.com/zhiwei2017/named_enum
